odoo/addons/stock_production_lot_active/README.rst
odoo/addons/stock_production_lot_active/__init__.py
odoo/addons/stock_production_lot_active/__manifest__.py
odoo/addons/stock_production_lot_active/i18n/es.po
odoo/addons/stock_production_lot_active/i18n/hr.po
odoo/addons/stock_production_lot_active/i18n/it.po
odoo/addons/stock_production_lot_active/i18n/stock_production_lot_active.pot
odoo/addons/stock_production_lot_active/models/__init__.py
odoo/addons/stock_production_lot_active/models/stock_production_lot.py
odoo/addons/stock_production_lot_active/readme/CONTRIBUTORS.md
odoo/addons/stock_production_lot_active/readme/DESCRIPTION.md
odoo/addons/stock_production_lot_active/static/description/icon.png
odoo/addons/stock_production_lot_active/static/description/index.html
odoo/addons/stock_production_lot_active/tests/__init__.py
odoo/addons/stock_production_lot_active/tests/test_lot_active.py
odoo/addons/stock_production_lot_active/views/stock_production_lot.xml
odoo_addon_stock_production_lot_active-18.0.1.0.0.4.dist-info/METADATA
odoo_addon_stock_production_lot_active-18.0.1.0.0.4.dist-info/WHEEL
odoo_addon_stock_production_lot_active-18.0.1.0.0.4.dist-info/top_level.txt
odoo_addon_stock_production_lot_active-18.0.1.0.0.4.dist-info/RECORD
